{
	"recipe": {
		"key": "copper_axe",
		"type": "SHAPED",
		"result": {
			"name": "STONE_AXE",
			"meta": {
				"display": "§f구리 도끼",
				"model": 0,
				"lore": [
					"§7재료 아이템의 등급이 높을수록,",
					"§7더 좋은 아이템을 조합할 수 있습니다.",
					"",
					"§7쉬프트 클릭으로 조합할 수 없습니다."
				],
				"flags": ["HIDE_ENCHANTS", "HIDE_ATTRIBUTES"]
			}
		},
		"shape": [
			"PP",
			"PS",
			" S"
		],
		"ingredients": {
			"P": "GOLD_NUGGET",
			"S": "STICK"
		},
		"ingredients_weight": {
			"GOLD_NUGGET": 1
		}
	},
	"pool": {
		"type": "entries_by_crafting_rank",
		"entries": [
			{
				"type": "rank",
				"weight": 5,
				"display": "부서질듯한 구리 도끼",
				"model": 0,
				"attributes": {
					"attack_damage": {
						"min": 5.200,
						"max": 5.200
					},
					"attack_speed": {
						"min": 1.5,
						"max": 2
					}
				}
			},
			{
				"type": "rank",
				"weight": 10,
				"display": "의미를 알 수 없는 구리 도끼",
				"model": 0,
				"attributes": {
					"attack_damage": {
						"min": 5.200,
						"max": 5.395
					},
					"attack_speed": {
						"min": 1.5,
						"max": 2
					}
				}
			},
			{
				"type": "rank",
				"weight": 10,
				"display": "제 기능을 하기 힘든 구리 도끼",
				"model": 0,
				"attributes": {
					"attack_damage": {
						"min": 5.330,
						"max": 5.720
					},
					"attack_speed": {
						"min": 1.5,
						"max": 2
					}
				}
			},
			{
				"type": "rank",
				"weight": 25,
				"display": "무딘 구리 도끼",
				"model": 0,
				"attributes": {
					"attack_damage": {
						"min": 5.590,
						"max": 6.175
					},
					"attack_speed": 2
				}
			},
			{
				"type": "rank",
				"weight": 35,
				"display": "무난한 구리 도끼",
				"model": 0,
				"attributes": {
					"attack_damage": {
						"min": 5.980,
						"max": 6.760
					},
					"attack_speed": 2
				}
			},
			{
				"type": "rank",
				"weight": 30,
				"quality": 0,
				"display": "평범한 구리 도끼",
				"model": 0,
				"attributes": {
					"attack_damage": {
						"min": 6.240,
						"max": 7.020
					},
					"attack_speed": 2
				}
			},
			{
				"type": "rank",
				"weight": 30,
				"quality": 0,
				"display": "쓸만한 구리 도끼",
				"model": 0,
				"attributes": {
					"attack_damage": {
						"min": 6.825,
						"max": 7.410
					},
					"attack_speed": 2
				}
			},
			{
				"type": "rank",
				"weight": 30,
				"display": "잘 만들어진 구리 도끼",
				"model": 0,
				"attributes": {
					"attack_damage": {
						"min": 7.280,
						"max": 7.670
					},
					"attack_speed": 2
				}
			},
			{
				"type": "rank",
				"weight": 20,
				"display": "예사롭지 않은 구리 도끼",
				"model": 0,
				"attributes": {
					"attack_damage": {
						"min": 7.605,
						"max": 7.800
					},
					"attack_speed": 2
				}
			},
			{
				"type": "rank",
				"weight": 1,
				"display": "전설적인 구리 도끼",
				"model": 0,
				"broadcast": true,
				"attributes": {
					"attack_damage": 7.800,
					"attack_speed": 2
				}
			}
		]
	}
}