{
	"recipe": {
		"key": "blackstone_pickaxe",
		"type": "SHAPED",
		"group": "stone_pickaxes",
		"result": {
			"name": "WOODEN_PICKAXE",
			"meta": {
				"display": "§f흑암 곡괭이",
				"model": 9,
				"lore": [
					"§7쉬프트 클릭으로 조합할 수 없습니다."
				],
				"flags": ["HIDE_ENCHANTS", "HIDE_ATTRIBUTES"]
			}
		},
		"shape": [
			"PPP",
			" S ",
			" S "
		],
		"ingredients": {
			"P": "BLACKSTONE",
			"S": "STICK"
		},
		"ingredients_weight": {
		}
	},
	"pool": {
		"type": "entries_by_crafting_rank",
		"entries": [
			{
				"type": "rank",
				"weight": 5,
				"display": "부서질듯한 흑암 곡괭이",
				"model": 9,
				"attributes": {
					"attack_damage": {
						"min": 3.0,
						"max": 3.3
					},
					"attack_speed": {
						"min": 2.0,
						"max": 2.5
					},
					"mining_power": {
						"min": 2.5,
						"max": 2.8
					}
				}
			},
			{
				"type": "rank",
				"weight": 10,
				"display": "의미를 알 수 없는 흑암 곡괭이",
				"model": 9,
				"attributes": {
					"attack_damage": {
						"min": 3.1,
						"max": 3.4
					},
					"attack_speed": {
						"min": 2.0,
						"max": 2.5
					},
					"mining_power": {
						"min": 2.6,
						"max": 2.9
					}
				}
			},
			{
				"type": "rank",
				"weight": 10,
				"display": "제 기능을 하기 힘든 흑암 곡괭이",
				"model": 9,
				"attributes": {
					"attack_damage": {
						"min": 3.2,
						"max": 3.5
					},
					"attack_speed": {
						"min": 2.0,
						"max": 2.5
					},
					"mining_power": {
						"min": 2.7,
						"max": 3.0
					}
				}
			},
			{
				"type": "rank",
				"weight": 25,
				"display": "무딘 흑암 곡괭이",
				"model": 9,
				"attributes": {
					"attack_damage": {
						"min": 3.3,
						"max": 3.6
					},
					"attack_speed": 2.5,
					"mining_power": {
						"min": 2.8,
						"max": 3.1
					}
				}
			},
			{
				"type": "rank",
				"weight": 35,
				"display": "무난한 흑암 곡괭이",
				"model": 9,
				"attributes": {
					"attack_damage": {
						"min": 3.5,
						"max": 3.8
					},
					"attack_speed": 2.5,
					"mining_power": {
						"min": 3.0,
						"max": 3.3
					}
				}
			},
			{
				"type": "rank",
				"weight": 30,
				"quality": 0,
				"display": "평범한 흑암 곡괭이",
				"model": 9,
				"attributes": {
					"attack_damage": {
						"min": 3.7,
						"max": 4.0
					},
					"attack_speed": 2.5,
					"mining_power": {
						"min": 3.2,
						"max": 3.5
					}
				}
			},
			{
				"type": "rank",
				"weight": 30,
				"quality": 0,
				"display": "쓸만한 흑암 곡괭이",
				"model": 9,
				"attributes": {
					"attack_damage": {
						"min": 3.9,
						"max": 4.2
					},
					"attack_speed": 2.5,
					"mining_power": {
						"min": 3.4,
						"max": 3.7
					}
				}
			},
			{
				"type": "rank",
				"weight": 30,
				"display": "잘 만들어진 흑암 곡괭이",
				"model": 9,
				"attributes": {
					"attack_damage": {
						"min": 4.1,
						"max": 4.4
					},
					"attack_speed": 2.5,
					"mining_power": {
						"min": 3.6,
						"max": 3.9
					}
				}
			},
			{
				"type": "rank",
				"weight": 20,
				"display": "예사롭지 않은 흑암 곡괭이",
				"model": 9,
				"attributes": {
					"attack_damage": {
						"min": 4.3,
						"max": 4.6
					},
					"attack_speed": 2.5,
					"mining_power": {
						"min": 3.8,
						"max": 4.1
					}
				}
			},
			{
				"type": "rank",
				"weight": 1,
				"display": "전설적인 흑암 곡괭이",
				"model": 9,
				"broadcast": true,
				"attributes": {
					"attack_damage": 5,
					"attack_speed": 2.5,
					"mining_power": 4.5
				}
			}
		]
	}
}